grid/__init__.py
grid/coord.py
grid/element.py
grid/grid.py
grid/hash.py
grid/network.py
gridcreator-0.2.0.dist-info/LICENSE
gridcreator-0.2.0.dist-info/METADATA
gridcreator-0.2.0.dist-info/WHEEL
gridcreator-0.2.0.dist-info/top_level.txt
gridcreator-0.2.0.dist-info/RECORD
