Metadata-Version: 2.1
Name: gridcreator
Version: 0.2.0
Summary: That library provides utilities to create grids.
Home-page: https://github.com/endprivate/grid
Author: oblivisheee
Author-email: molniya213y@proton.me
License: GNU General Public License Version 3
License-File: LICENSE
Requires-Dist: numpy
